healthcheck_lite/__main__.py
healthcheck_lite-1.0.2.dist-info/METADATA
healthcheck_lite-1.0.2.dist-info/WHEEL
healthcheck_lite-1.0.2.dist-info/entry_points.txt
healthcheck_lite-1.0.2.dist-info/top_level.txt
healthcheck_lite-1.0.2.dist-info/RECORD
