Metadata-Version: 2.4
Name: healthcheck-lite
Version: 1.0.2
Summary: A lightweight and configurable system healthcheck tool for Linux
Author-email: Emmanuel Bocquet <manu@unixdev.ca>
License-Expression: MIT
Classifier: Programming Language :: Python :: 3
Classifier: Operating System :: POSIX :: Linux
Classifier: Intended Audience :: System Administrators
Classifier: Topic :: System :: Monitoring
Requires-Python: >=3.6
Requires-Dist: psutil
